odoo/addons/product_pricelist_simulation/README.rst
odoo/addons/product_pricelist_simulation/__init__.py
odoo/addons/product_pricelist_simulation/__manifest__.py
odoo/addons/product_pricelist_simulation/i18n/es.po
odoo/addons/product_pricelist_simulation/i18n/it.po
odoo/addons/product_pricelist_simulation/i18n/product_pricelist_simulation.pot
odoo/addons/product_pricelist_simulation/i18n/pt_BR.po
odoo/addons/product_pricelist_simulation/i18n/tr.po
odoo/addons/product_pricelist_simulation/models/__init__.py
odoo/addons/product_pricelist_simulation/models/pricelist.py
odoo/addons/product_pricelist_simulation/readme/CONTRIBUTORS.md
odoo/addons/product_pricelist_simulation/readme/DESCRIPTION.md
odoo/addons/product_pricelist_simulation/readme/USAGE.md
odoo/addons/product_pricelist_simulation/security/ir.model.access.csv
odoo/addons/product_pricelist_simulation/static/description/icon.png
odoo/addons/product_pricelist_simulation/static/description/index.html
odoo/addons/product_pricelist_simulation/tests/__init__.py
odoo/addons/product_pricelist_simulation/tests/test_product_pricelist_simulation.py
odoo/addons/product_pricelist_simulation/views/pricelist_views.xml
odoo/addons/product_pricelist_simulation/views/product_views.xml
odoo/addons/product_pricelist_simulation/wizards/__init__.py
odoo/addons/product_pricelist_simulation/wizards/wizard_preview_pricelist.py
odoo/addons/product_pricelist_simulation/wizards/wizard_preview_pricelist_views.xml
odoo_addon_product_pricelist_simulation-17.0.1.0.0.3.dist-info/METADATA
odoo_addon_product_pricelist_simulation-17.0.1.0.0.3.dist-info/WHEEL
odoo_addon_product_pricelist_simulation-17.0.1.0.0.3.dist-info/top_level.txt
odoo_addon_product_pricelist_simulation-17.0.1.0.0.3.dist-info/RECORD
